yolo_minimal_inference/__init__.py
yolo_minimal_inference/__main__.py
yolo_minimal_inference/cv.py
yolo_minimal_inference/trackers/basetrack.py
yolo_minimal_inference/trackers/bot_sort.py
yolo_minimal_inference/trackers/byte_tracker.py
yolo_minimal_inference/trackers/utils/kalman_filter.py
yolo_minimal_inference/trackers/utils/matching.py
yolo_minimal_inference/utils.py
yolo_minimal_inference/yolo.py
yolo_minimal_inference-0.1.9.dist-info/METADATA
yolo_minimal_inference-0.1.9.dist-info/WHEEL
yolo_minimal_inference-0.1.9.dist-info/entry_points.txt
yolo_minimal_inference-0.1.9.dist-info/RECORD
