Metadata-Version: 2.3
Name: yolo-minimal-inference
Version: 0.1.9
Summary: A Python package to run YOLO models using ONNX Runtime
Author: Daniel García Peña
Author-email: info@iamdgarcia.com
Requires-Python: >=3.9,<4.0
Classifier: Programming Language :: Python :: 3
Classifier: Programming Language :: Python :: 3.9
Classifier: Programming Language :: Python :: 3.10
Classifier: Programming Language :: Python :: 3.11
Classifier: Programming Language :: Python :: 3.12
Classifier: Programming Language :: Python :: 3.13
Requires-Dist: imageio (>=2.37.0,<3.0.0)
Requires-Dist: onnxruntime (>=1.19.0,<2.0.0)
